sparta_auth0-1.0.0-py3.11-nspkg.pth
sparta/auth0/__init__.py
sparta/auth0/token_provider.py
sparta/auth0/token_verifier.py
sparta_auth0-1.0.0.dist-info/LICENSE
sparta_auth0-1.0.0.dist-info/METADATA
sparta_auth0-1.0.0.dist-info/WHEEL
sparta_auth0-1.0.0.dist-info/namespace_packages.txt
sparta_auth0-1.0.0.dist-info/top_level.txt
sparta_auth0-1.0.0.dist-info/RECORD
