Metadata-Version: 2.1
Name: sparta-auth0
Version: 1.0.0
Summary: Sparta Auth0 library
Home-page: https://github.com/Spartan-Approach/sparta-auth0
Author: Spartan Approach
Author-email: sparta@spartanapproach.com
Classifier: Development Status :: 4 - Beta
Classifier: Programming Language :: Python :: 3
Classifier: License :: OSI Approved :: MIT License
Classifier: Operating System :: OS Independent
Requires-Python: >=3.9
License-File: LICENSE
Requires-Dist: python-jose
Provides-Extra: test
Requires-Dist: pytest ; extra == 'test'
